{
  "allGaps": [
    {
      "id": "ILS-CONST-INCOMPLETE",
      "description": "Constitutional Layer missing one or more of the 5 Core Rules",
      "severity": 9,
      "evidence": "Not all RULE 1-5 markers found in constitutional-layer-v3.md",
      "impact30d": "Degraded reasoning quality; outputs may lack depth or evidence",
      "reportedBy": "sutskever"
    },
    {
      "id": "ILS-PROTO-INCOMPLETE",
      "description": "Constitutional Layer missing Protocol Extensions",
      "severity": 7,
      "evidence": "Not all P1-P5 protocol markers found",
      "impact30d": "Missing Karpathy anchoring, Ng workflows, or Nakajima self-improvement signals",
      "reportedBy": "sutskever"
    },
    {
      "id": "HAS-BASELINE-ZERO",
      "description": "Quality baseline not yet established — no session scores recorded",
      "severity": 7,
      "evidence": "current_baseline: 4.9, trend: establishing",
      "impact30d": "No quality trend tracking; unable to detect regression or improvement",
      "reportedBy": "hassabis"
    },
    {
      "id": "PED-STRUCT-.aios-core",
      "description": "Required directory \".aios-core\" not found in project structure",
      "severity": 7,
      "evidence": "No files found with this prefix",
      "impact30d": "Breaks the \"Structure is Sacred\" principle from AIOS philosophy",
      "reportedBy": "pedro"
    },
    {
      "id": "ALN-README-MISSING",
      "description": "README.md missing or empty — product not self-documenting",
      "severity": 7,
      "evidence": "README.md not found in scan",
      "impact30d": "New users/agents cannot onboard; product fails 60-second test",
      "reportedBy": "alan"
    },
    {
      "id": "DST-TRACES-MISSING",
      "description": "Distillation traces directory not found — reasoning traces not being captured",
      "severity": 7,
      "evidence": "distillation-dataset/traces/ not found",
      "impact30d": "Every cycle produces reasoning traces that are lost forever. Zero progress toward local model independence.",
      "reportedBy": "distillation"
    },
    {
      "id": "KAR-ERRH-activate-kernel.js",
      "description": "scripts/activate-kernel.js has external calls without try-catch error handling",
      "severity": 6,
      "evidence": "Has require()/fetch() but no try-catch blocks",
      "impact30d": "Silent failures in production; AP-002 pattern",
      "reportedBy": "karpathy"
    },
    {
      "id": "KAR-ERRH-activate-registry.js",
      "description": "scripts/activate-registry.js has external calls without try-catch error handling",
      "severity": 6,
      "evidence": "Has require()/fetch() but no try-catch blocks",
      "impact30d": "Silent failures in production; AP-002 pattern",
      "reportedBy": "karpathy"
    },
    {
      "id": "KAR-ERRH-audit-squad-agents.js",
      "description": "scripts/audit-squad-agents.js has external calls without try-catch error handling",
      "severity": 6,
      "evidence": "Has require()/fetch() but no try-catch blocks",
      "impact30d": "Silent failures in production; AP-002 pattern",
      "reportedBy": "karpathy"
    },
    {
      "id": "KAR-ERRH-bridge-auth.js",
      "description": "scripts/bridge-auth.js has external calls without try-catch error handling",
      "severity": 6,
      "evidence": "Has require()/fetch() but no try-catch blocks",
      "impact30d": "Silent failures in production; AP-002 pattern",
      "reportedBy": "karpathy"
    },
    {
      "id": "KAR-ERRH-clickup-client.js",
      "description": "scripts/clickup-client.js has external calls without try-catch error handling",
      "severity": 6,
      "evidence": "Has require()/fetch() but no try-catch blocks",
      "impact30d": "Silent failures in production; AP-002 pattern",
      "reportedBy": "karpathy"
    },
    {
      "id": "KAR-ERRH-clickup-workspace-builder.js",
      "description": "scripts/clickup-workspace-builder.js has external calls without try-catch error handling",
      "severity": 6,
      "evidence": "Has require()/fetch() but no try-catch blocks",
      "impact30d": "Silent failures in production; AP-002 pattern",
      "reportedBy": "karpathy"
    },
    {
      "id": "KAR-ERRH-clickup-workspace-fix.js",
      "description": "scripts/clickup-workspace-fix.js has external calls without try-catch error handling",
      "severity": 6,
      "evidence": "Has require()/fetch() but no try-catch blocks",
      "impact30d": "Silent failures in production; AP-002 pattern",
      "reportedBy": "karpathy"
    },
    {
      "id": "KAR-ERRH-codespaces-tunnel.js",
      "description": "scripts/codespaces-tunnel.js has external calls without try-catch error handling",
      "severity": 6,
      "evidence": "Has require()/fetch() but no try-catch blocks",
      "impact30d": "Silent failures in production; AP-002 pattern",
      "reportedBy": "karpathy"
    },
    {
      "id": "KAR-ERRH-email-client.js",
      "description": "scripts/email-client.js has external calls without try-catch error handling",
      "severity": 6,
      "evidence": "Has require()/fetch() but no try-catch blocks",
      "impact30d": "Silent failures in production; AP-002 pattern",
      "reportedBy": "karpathy"
    },
    {
      "id": "KAR-ERRH-event-bus.js",
      "description": "scripts/event-bus.js has external calls without try-catch error handling",
      "severity": 6,
      "evidence": "Has require()/fetch() but no try-catch blocks",
      "impact30d": "Silent failures in production; AP-002 pattern",
      "reportedBy": "karpathy"
    },
    {
      "id": "KAR-ERRH-experia-content.js",
      "description": "scripts/experia-content.js has external calls without try-catch error handling",
      "severity": 6,
      "evidence": "Has require()/fetch() but no try-catch blocks",
      "impact30d": "Silent failures in production; AP-002 pattern",
      "reportedBy": "karpathy"
    },
    {
      "id": "KAR-ERRH-experia-sdr.js",
      "description": "scripts/experia-sdr.js has external calls without try-catch error handling",
      "severity": 6,
      "evidence": "Has require()/fetch() but no try-catch blocks",
      "impact30d": "Silent failures in production; AP-002 pattern",
      "reportedBy": "karpathy"
    },
    {
      "id": "KAR-ERRH-generate-install-manifest.js",
      "description": "scripts/generate-install-manifest.js has external calls without try-catch error handling",
      "severity": 6,
      "evidence": "Has require()/fetch() but no try-catch blocks",
      "impact30d": "Silent failures in production; AP-002 pattern",
      "reportedBy": "karpathy"
    },
    {
      "id": "KAR-ERRH-gsheets-client.js",
      "description": "scripts/gsheets-client.js has external calls without try-catch error handling",
      "severity": 6,
      "evidence": "Has require()/fetch() but no try-catch blocks",
      "impact30d": "Silent failures in production; AP-002 pattern",
      "reportedBy": "karpathy"
    },
    {
      "id": "KAR-ERRH-instagram-client.js",
      "description": "scripts/instagram-client.js has external calls without try-catch error handling",
      "severity": 6,
      "evidence": "Has require()/fetch() but no try-catch blocks",
      "impact30d": "Silent failures in production; AP-002 pattern",
      "reportedBy": "karpathy"
    },
    {
      "id": "KAR-ERRH-keep-alive.js",
      "description": "scripts/keep-alive.js has external calls without try-catch error handling",
      "severity": 6,
      "evidence": "Has require()/fetch() but no try-catch blocks",
      "impact30d": "Silent failures in production; AP-002 pattern",
      "reportedBy": "karpathy"
    },
    {
      "id": "KAR-ERRH-livestream-extractor.js",
      "description": "scripts/livestream-extractor.js has external calls without try-catch error handling",
      "severity": 6,
      "evidence": "Has require()/fetch() but no try-catch blocks",
      "impact30d": "Silent failures in production; AP-002 pattern",
      "reportedBy": "karpathy"
    },
    {
      "id": "KAR-ERRH-mcp-server.js",
      "description": "scripts/mcp-server.js has external calls without try-catch error handling",
      "severity": 6,
      "evidence": "Has require()/fetch() but no try-catch blocks",
      "impact30d": "Silent failures in production; AP-002 pattern",
      "reportedBy": "karpathy"
    },
    {
      "id": "KAR-ERRH-memory-system.js",
      "description": "scripts/memory-system.js has external calls without try-catch error handling",
      "severity": 6,
      "evidence": "Has require()/fetch() but no try-catch blocks",
      "impact30d": "Silent failures in production; AP-002 pattern",
      "reportedBy": "karpathy"
    },
    {
      "id": "KAR-ERRH-night-shift-automator.js",
      "description": "scripts/night-shift-automator.js has external calls without try-catch error handling",
      "severity": 6,
      "evidence": "Has require()/fetch() but no try-catch blocks",
      "impact30d": "Silent failures in production; AP-002 pattern",
      "reportedBy": "karpathy"
    },
    {
      "id": "KAR-ERRH-night-shift-scheduler.js",
      "description": "scripts/night-shift-scheduler.js has external calls without try-catch error handling",
      "severity": 6,
      "evidence": "Has require()/fetch() but no try-catch blocks",
      "impact30d": "Silent failures in production; AP-002 pattern",
      "reportedBy": "karpathy"
    },
    {
      "id": "KAR-ERRH-noesis-hook.js",
      "description": "scripts/noesis-hook.js has external calls without try-catch error handling",
      "severity": 6,
      "evidence": "Has require()/fetch() but no try-catch blocks",
      "impact30d": "Silent failures in production; AP-002 pattern",
      "reportedBy": "karpathy"
    },
    {
      "id": "KAR-ERRH-package-synapse.js",
      "description": "scripts/package-synapse.js has external calls without try-catch error handling",
      "severity": 6,
      "evidence": "Has require()/fetch() but no try-catch blocks",
      "impact30d": "Silent failures in production; AP-002 pattern",
      "reportedBy": "karpathy"
    },
    {
      "id": "KAR-ERRH-semantic-lint.js",
      "description": "scripts/semantic-lint.js has external calls without try-catch error handling",
      "severity": 6,
      "evidence": "Has require()/fetch() but no try-catch blocks",
      "impact30d": "Silent failures in production; AP-002 pattern",
      "reportedBy": "karpathy"
    },
    {
      "id": "KAR-ERRH-upgrade-admin-produto-facilities.js",
      "description": "scripts/upgrade-admin-produto-facilities.js has external calls without try-catch error handling",
      "severity": 6,
      "evidence": "Has require()/fetch() but no try-catch blocks",
      "impact30d": "Silent failures in production; AP-002 pattern",
      "reportedBy": "karpathy"
    },
    {
      "id": "KAR-ERRH-upgrade-cs.js",
      "description": "scripts/upgrade-cs.js has external calls without try-catch error handling",
      "severity": 6,
      "evidence": "Has require()/fetch() but no try-catch blocks",
      "impact30d": "Silent failures in production; AP-002 pattern",
      "reportedBy": "karpathy"
    },
    {
      "id": "KAR-ERRH-upgrade-ops.js",
      "description": "scripts/upgrade-ops.js has external calls without try-catch error handling",
      "severity": 6,
      "evidence": "Has require()/fetch() but no try-catch blocks",
      "impact30d": "Silent failures in production; AP-002 pattern",
      "reportedBy": "karpathy"
    },
    {
      "id": "KAR-ERRH-validate-aiox-core-deps.js",
      "description": "scripts/validate-aiox-core-deps.js has external calls without try-catch error handling",
      "severity": 6,
      "evidence": "Has require()/fetch() but no try-catch blocks",
      "impact30d": "Silent failures in production; AP-002 pattern",
      "reportedBy": "karpathy"
    },
    {
      "id": "KAR-ERRH-validate-manifest.js",
      "description": "scripts/validate-manifest.js has external calls without try-catch error handling",
      "severity": 6,
      "evidence": "Has require()/fetch() but no try-catch blocks",
      "impact30d": "Silent failures in production; AP-002 pattern",
      "reportedBy": "karpathy"
    },
    {
      "id": "KAR-ERRH-vod-transcriber.js",
      "description": "scripts/vod-transcriber.js has external calls without try-catch error handling",
      "severity": 6,
      "evidence": "Has require()/fetch() but no try-catch blocks",
      "impact30d": "Silent failures in production; AP-002 pattern",
      "reportedBy": "karpathy"
    },
    {
      "id": "KAR-ERRH-operator-noesis-engine.js",
      "description": "scripts/operator-noesis/operator-noesis-engine.js has external calls without try-catch error handling",
      "severity": 6,
      "evidence": "Has require()/fetch() but no try-catch blocks",
      "impact30d": "Silent failures in production; AP-002 pattern",
      "reportedBy": "karpathy"
    },
    {
      "id": "HIN-CONTEXT-STALE",
      "description": "SELF_CONTEXT.md last updated 21 days ago",
      "severity": 6,
      "evidence": "Last update: 2026-02-20T02:50:00-03:00",
      "impact30d": "New sessions boot with outdated context; decisions based on stale information",
      "reportedBy": "hinton"
    },
    {
      "id": "DST-CURATED-MISSING",
      "description": "Curated dataset directory not found — high-quality examples not being collected",
      "severity": 6,
      "evidence": "distillation-dataset/curated/ not found",
      "impact30d": "Golden examples exist but are not structured for fine-tuning. Model training impossible.",
      "reportedBy": "distillation"
    },
    {
      "id": "KAR-JSDOC-aios-kairos-bridge.js",
      "description": "scripts/aios-kairos-bridge.js lacks comprehensive JSDoc with @purpose annotation",
      "severity": 4,
      "evidence": "File has JSDoc blocks, no @purpose tag",
      "impact30d": "Reduced maintainability; new agents cannot understand module contracts",
      "reportedBy": "karpathy"
    },
    {
      "id": "KAR-JSDOC-code-intel-health-check.js",
      "description": "scripts/code-intel-health-check.js lacks comprehensive JSDoc with @purpose annotation",
      "severity": 4,
      "evidence": "File has JSDoc blocks, no @purpose tag",
      "impact30d": "Reduced maintainability; new agents cannot understand module contracts",
      "reportedBy": "karpathy"
    },
    {
      "id": "KAR-JSDOC-dump-council.js",
      "description": "scripts/dump-council.js lacks comprehensive JSDoc with @purpose annotation",
      "severity": 4,
      "evidence": "File has no JSDoc blocks, no @purpose tag",
      "impact30d": "Reduced maintainability; new agents cannot understand module contracts",
      "reportedBy": "karpathy"
    },
    {
      "id": "KAR-JSDOC-ensure-manifest.js",
      "description": "scripts/ensure-manifest.js lacks comprehensive JSDoc with @purpose annotation",
      "severity": 4,
      "evidence": "File has no JSDoc blocks, no @purpose tag",
      "impact30d": "Reduced maintainability; new agents cannot understand module contracts",
      "reportedBy": "karpathy"
    },
    {
      "id": "KAR-JSDOC-generate-install-manifest.js",
      "description": "scripts/generate-install-manifest.js lacks comprehensive JSDoc with @purpose annotation",
      "severity": 4,
      "evidence": "File has JSDoc blocks, no @purpose tag",
      "impact30d": "Reduced maintainability; new agents cannot understand module contracts",
      "reportedBy": "karpathy"
    },
    {
      "id": "KAR-JSDOC-jarvis-core.js",
      "description": "scripts/jarvis-core.js lacks comprehensive JSDoc with @purpose annotation",
      "severity": 4,
      "evidence": "File has JSDoc blocks, no @purpose tag",
      "impact30d": "Reduced maintainability; new agents cannot understand module contracts",
      "reportedBy": "karpathy"
    },
    {
      "id": "KAR-JSDOC-livestream-extractor.js",
      "description": "scripts/livestream-extractor.js lacks comprehensive JSDoc with @purpose annotation",
      "severity": 4,
      "evidence": "File has no JSDoc blocks, no @purpose tag",
      "impact30d": "Reduced maintainability; new agents cannot understand module contracts",
      "reportedBy": "karpathy"
    },
    {
      "id": "KAR-JSDOC-night-shift-automator.js",
      "description": "scripts/night-shift-automator.js lacks comprehensive JSDoc with @purpose annotation",
      "severity": 4,
      "evidence": "File has no JSDoc blocks, no @purpose tag",
      "impact30d": "Reduced maintainability; new agents cannot understand module contracts",
      "reportedBy": "karpathy"
    },
    {
      "id": "KAR-JSDOC-night-shift-scheduler.js",
      "description": "scripts/night-shift-scheduler.js lacks comprehensive JSDoc with @purpose annotation",
      "severity": 4,
      "evidence": "File has JSDoc blocks, no @purpose tag",
      "impact30d": "Reduced maintainability; new agents cannot understand module contracts",
      "reportedBy": "karpathy"
    },
    {
      "id": "KAR-JSDOC-inference-validator.js",
      "description": "scripts/operator-noesis/inference-validator.js lacks comprehensive JSDoc with @purpose annotation",
      "severity": 4,
      "evidence": "File has JSDoc blocks, no @purpose tag",
      "impact30d": "Reduced maintainability; new agents cannot understand module contracts",
      "reportedBy": "karpathy"
    },
    {
      "id": "KAR-JSDOC-learning-model-evaluator.js",
      "description": "scripts/operator-noesis/learning-model-evaluator.js lacks comprehensive JSDoc with @purpose annotation",
      "severity": 4,
      "evidence": "File has JSDoc blocks, no @purpose tag",
      "impact30d": "Reduced maintainability; new agents cannot understand module contracts",
      "reportedBy": "karpathy"
    },
    {
      "id": "KAR-JSDOC-model-updater.js",
      "description": "scripts/operator-noesis/model-updater.js lacks comprehensive JSDoc with @purpose annotation",
      "severity": 4,
      "evidence": "File has JSDoc blocks, no @purpose tag",
      "impact30d": "Reduced maintainability; new agents cannot understand module contracts",
      "reportedBy": "karpathy"
    },
    {
      "id": "KAR-JSDOC-operator-noesis-engine.js",
      "description": "scripts/operator-noesis/operator-noesis-engine.js lacks comprehensive JSDoc with @purpose annotation",
      "severity": 4,
      "evidence": "File has JSDoc blocks, no @purpose tag",
      "impact30d": "Reduced maintainability; new agents cannot understand module contracts",
      "reportedBy": "karpathy"
    },
    {
      "id": "KAR-JSDOC-operator-noesis-gate.js",
      "description": "scripts/operator-noesis/operator-noesis-gate.js lacks comprehensive JSDoc with @purpose annotation",
      "severity": 4,
      "evidence": "File has JSDoc blocks, no @purpose tag",
      "impact30d": "Reduced maintainability; new agents cannot understand module contracts",
      "reportedBy": "karpathy"
    },
    {
      "id": "KAR-JSDOC-package-synapse.js",
      "description": "scripts/package-synapse.js lacks comprehensive JSDoc with @purpose annotation",
      "severity": 4,
      "evidence": "File has JSDoc blocks, no @purpose tag",
      "impact30d": "Reduced maintainability; new agents cannot understand module contracts",
      "reportedBy": "karpathy"
    },
    {
      "id": "KAR-JSDOC-profile-enricher.js",
      "description": "scripts/profile-enricher.js lacks comprehensive JSDoc with @purpose annotation",
      "severity": 4,
      "evidence": "File has JSDoc blocks, no @purpose tag",
      "impact30d": "Reduced maintainability; new agents cannot understand module contracts",
      "reportedBy": "karpathy"
    },
    {
      "id": "KAR-JSDOC-semantic-lint.js",
      "description": "scripts/semantic-lint.js lacks comprehensive JSDoc with @purpose annotation",
      "severity": 4,
      "evidence": "File has no JSDoc blocks, no @purpose tag",
      "impact30d": "Reduced maintainability; new agents cannot understand module contracts",
      "reportedBy": "karpathy"
    },
    {
      "id": "KAR-JSDOC-validate-aiox-core-deps.js",
      "description": "scripts/validate-aiox-core-deps.js lacks comprehensive JSDoc with @purpose annotation",
      "severity": 4,
      "evidence": "File has JSDoc blocks, no @purpose tag",
      "impact30d": "Reduced maintainability; new agents cannot understand module contracts",
      "reportedBy": "karpathy"
    },
    {
      "id": "KAR-JSDOC-validate-manifest.js",
      "description": "scripts/validate-manifest.js lacks comprehensive JSDoc with @purpose annotation",
      "severity": 4,
      "evidence": "File has JSDoc blocks, no @purpose tag",
      "impact30d": "Reduced maintainability; new agents cannot understand module contracts",
      "reportedBy": "karpathy"
    },
    {
      "id": "KAR-JSDOC-validate-package-completeness.js",
      "description": "scripts/validate-package-completeness.js lacks comprehensive JSDoc with @purpose annotation",
      "severity": 4,
      "evidence": "File has JSDoc blocks, no @purpose tag",
      "impact30d": "Reduced maintainability; new agents cannot understand module contracts",
      "reportedBy": "karpathy"
    },
    {
      "id": "KAR-JSDOC-vod-transcriber.js",
      "description": "scripts/vod-transcriber.js lacks comprehensive JSDoc with @purpose annotation",
      "severity": 4,
      "evidence": "File has no JSDoc blocks, no @purpose tag",
      "impact30d": "Reduced maintainability; new agents cannot understand module contracts",
      "reportedBy": "karpathy"
    },
    {
      "id": "KAR-JSDOC-inference-validator.js",
      "description": "scripts/operator-noesis/inference-validator.js lacks comprehensive JSDoc with @purpose annotation",
      "severity": 4,
      "evidence": "File has JSDoc blocks, no @purpose tag",
      "impact30d": "Reduced maintainability; new agents cannot understand module contracts",
      "reportedBy": "karpathy"
    },
    {
      "id": "KAR-JSDOC-learning-model-evaluator.js",
      "description": "scripts/operator-noesis/learning-model-evaluator.js lacks comprehensive JSDoc with @purpose annotation",
      "severity": 4,
      "evidence": "File has JSDoc blocks, no @purpose tag",
      "impact30d": "Reduced maintainability; new agents cannot understand module contracts",
      "reportedBy": "karpathy"
    },
    {
      "id": "KAR-JSDOC-model-updater.js",
      "description": "scripts/operator-noesis/model-updater.js lacks comprehensive JSDoc with @purpose annotation",
      "severity": 4,
      "evidence": "File has JSDoc blocks, no @purpose tag",
      "impact30d": "Reduced maintainability; new agents cannot understand module contracts",
      "reportedBy": "karpathy"
    },
    {
      "id": "KAR-JSDOC-operator-noesis-engine.js",
      "description": "scripts/operator-noesis/operator-noesis-engine.js lacks comprehensive JSDoc with @purpose annotation",
      "severity": 4,
      "evidence": "File has JSDoc blocks, no @purpose tag",
      "impact30d": "Reduced maintainability; new agents cannot understand module contracts",
      "reportedBy": "karpathy"
    },
    {
      "id": "KAR-JSDOC-operator-noesis-gate.js",
      "description": "scripts/operator-noesis/operator-noesis-gate.js lacks comprehensive JSDoc with @purpose annotation",
      "severity": 4,
      "evidence": "File has JSDoc blocks, no @purpose tag",
      "impact30d": "Reduced maintainability; new agents cannot understand module contracts",
      "reportedBy": "karpathy"
    },
    {
      "id": "NG-DUP-generateClonePrompt",
      "description": "Function \"generateClonePrompt\" defined in multiple files: scripts/evolution/clone-generator.js, scripts/evolution/clone-generator.js",
      "severity": 4,
      "evidence": "2 definitions found",
      "impact30d": "Maintenance burden; changes need to be replicated across files",
      "reportedBy": "ng"
    },
    {
      "id": "NG-DUP-write",
      "description": "Function \"write\" defined in multiple files: scripts/upgrade-admin-produto-facilities.js, scripts/upgrade-cs.js, scripts/upgrade-ops.js",
      "severity": 4,
      "evidence": "3 definitions found",
      "impact30d": "Maintenance burden; changes need to be replicated across files",
      "reportedBy": "ng"
    },
    {
      "id": "HAS-MEM-MISSING",
      "description": "No memory.json found — memory system may not be active",
      "severity": 4,
      "evidence": "data/memory.json not found in file scan",
      "impact30d": "Decisions and metrics not being persisted between sessions",
      "reportedBy": "hassabis"
    },
    {
      "id": "DST-PATTERN-README.md",
      "description": "Golden example engine/opus-replicator/golden-examples/README.md solves a specific problem but doesn't teach a generalizable pattern",
      "severity": 3,
      "evidence": "No PATTERN: marker or pattern_type field found",
      "impact30d": "Example useful for reference but cannot train a model to generalize",
      "reportedBy": "distillation"
    },
    {
      "id": "NG-UNUSED-activate-kernel",
      "description": "scripts/activate-kernel.js is not referenced by any other script",
      "severity": 2,
      "evidence": "No cross-references found in other scripts",
      "impact30d": "Dead code; cognitive load for new developers",
      "reportedBy": "ng"
    },
    {
      "id": "NG-UNUSED-activate-registry",
      "description": "scripts/activate-registry.js is not referenced by any other script",
      "severity": 2,
      "evidence": "No cross-references found in other scripts",
      "impact30d": "Dead code; cognitive load for new developers",
      "reportedBy": "ng"
    },
    {
      "id": "NG-UNUSED-aios-kairos-bridge",
      "description": "scripts/aios-kairos-bridge.js is not referenced by any other script",
      "severity": 2,
      "evidence": "No cross-references found in other scripts",
      "impact30d": "Dead code; cognitive load for new developers",
      "reportedBy": "ng"
    },
    {
      "id": "NG-UNUSED-audit-squad-agents",
      "description": "scripts/audit-squad-agents.js is not referenced by any other script",
      "severity": 2,
      "evidence": "No cross-references found in other scripts",
      "impact30d": "Dead code; cognitive load for new developers",
      "reportedBy": "ng"
    },
    {
      "id": "NG-UNUSED-clickup-client",
      "description": "scripts/clickup-client.js is not referenced by any other script",
      "severity": 2,
      "evidence": "No cross-references found in other scripts",
      "impact30d": "Dead code; cognitive load for new developers",
      "reportedBy": "ng"
    },
    {
      "id": "NG-UNUSED-clickup-workspace-builder",
      "description": "scripts/clickup-workspace-builder.js is not referenced by any other script",
      "severity": 2,
      "evidence": "No cross-references found in other scripts",
      "impact30d": "Dead code; cognitive load for new developers",
      "reportedBy": "ng"
    },
    {
      "id": "NG-UNUSED-clickup-workspace-fix",
      "description": "scripts/clickup-workspace-fix.js is not referenced by any other script",
      "severity": 2,
      "evidence": "No cross-references found in other scripts",
      "impact30d": "Dead code; cognitive load for new developers",
      "reportedBy": "ng"
    },
    {
      "id": "NG-UNUSED-code-intel-health-check",
      "description": "scripts/code-intel-health-check.js is not referenced by any other script",
      "severity": 2,
      "evidence": "No cross-references found in other scripts",
      "impact30d": "Dead code; cognitive load for new developers",
      "reportedBy": "ng"
    },
    {
      "id": "NG-UNUSED-codespaces-tunnel",
      "description": "scripts/codespaces-tunnel.js is not referenced by any other script",
      "severity": 2,
      "evidence": "No cross-references found in other scripts",
      "impact30d": "Dead code; cognitive load for new developers",
      "reportedBy": "ng"
    },
    {
      "id": "NG-UNUSED-jarvis-pipeline",
      "description": "scripts/data-ingestion/jarvis-pipeline.js is not referenced by any other script",
      "severity": 2,
      "evidence": "No cross-references found in other scripts",
      "impact30d": "Dead code; cognitive load for new developers",
      "reportedBy": "ng"
    },
    {
      "id": "NG-UNUSED-dump-council",
      "description": "scripts/dump-council.js is not referenced by any other script",
      "severity": 2,
      "evidence": "No cross-references found in other scripts",
      "impact30d": "Dead code; cognitive load for new developers",
      "reportedBy": "ng"
    },
    {
      "id": "NG-UNUSED-email-client",
      "description": "scripts/email-client.js is not referenced by any other script",
      "severity": 2,
      "evidence": "No cross-references found in other scripts",
      "impact30d": "Dead code; cognitive load for new developers",
      "reportedBy": "ng"
    },
    {
      "id": "NG-UNUSED-ensure-manifest",
      "description": "scripts/ensure-manifest.js is not referenced by any other script",
      "severity": 2,
      "evidence": "No cross-references found in other scripts",
      "impact30d": "Dead code; cognitive load for new developers",
      "reportedBy": "ng"
    },
    {
      "id": "NG-UNUSED-clone-generator",
      "description": "scripts/evolution/clone-generator.js is not referenced by any other script",
      "severity": 2,
      "evidence": "No cross-references found in other scripts",
      "impact30d": "Dead code; cognitive load for new developers",
      "reportedBy": "ng"
    },
    {
      "id": "NG-UNUSED-experia-content",
      "description": "scripts/experia-content.js is not referenced by any other script",
      "severity": 2,
      "evidence": "No cross-references found in other scripts",
      "impact30d": "Dead code; cognitive load for new developers",
      "reportedBy": "ng"
    },
    {
      "id": "NG-UNUSED-experia-sdr",
      "description": "scripts/experia-sdr.js is not referenced by any other script",
      "severity": 2,
      "evidence": "No cross-references found in other scripts",
      "impact30d": "Dead code; cognitive load for new developers",
      "reportedBy": "ng"
    },
    {
      "id": "NG-UNUSED-gsheets-client",
      "description": "scripts/gsheets-client.js is not referenced by any other script",
      "severity": 2,
      "evidence": "No cross-references found in other scripts",
      "impact30d": "Dead code; cognitive load for new developers",
      "reportedBy": "ng"
    },
    {
      "id": "NG-UNUSED-harvest-gold",
      "description": "scripts/harvest-gold.js is not referenced by any other script",
      "severity": 2,
      "evidence": "No cross-references found in other scripts",
      "impact30d": "Dead code; cognitive load for new developers",
      "reportedBy": "ng"
    },
    {
      "id": "NG-UNUSED-input-refiner",
      "description": "scripts/input-refiner.js is not referenced by any other script",
      "severity": 2,
      "evidence": "No cross-references found in other scripts",
      "impact30d": "Dead code; cognitive load for new developers",
      "reportedBy": "ng"
    },
    {
      "id": "NG-UNUSED-instagram-client",
      "description": "scripts/instagram-client.js is not referenced by any other script",
      "severity": 2,
      "evidence": "No cross-references found in other scripts",
      "impact30d": "Dead code; cognitive load for new developers",
      "reportedBy": "ng"
    },
    {
      "id": "NG-UNUSED-jan-connector",
      "description": "scripts/jan-connector.js is not referenced by any other script",
      "severity": 2,
      "evidence": "No cross-references found in other scripts",
      "impact30d": "Dead code; cognitive load for new developers",
      "reportedBy": "ng"
    },
    {
      "id": "NG-UNUSED-kairos-boot",
      "description": "scripts/kairos-boot.js is not referenced by any other script",
      "severity": 2,
      "evidence": "No cross-references found in other scripts",
      "impact30d": "Dead code; cognitive load for new developers",
      "reportedBy": "ng"
    },
    {
      "id": "NG-UNUSED-keep-alive",
      "description": "scripts/keep-alive.js is not referenced by any other script",
      "severity": 2,
      "evidence": "No cross-references found in other scripts",
      "impact30d": "Dead code; cognitive load for new developers",
      "reportedBy": "ng"
    },
    {
      "id": "NG-UNUSED-livestream-extractor",
      "description": "scripts/livestream-extractor.js is not referenced by any other script",
      "severity": 2,
      "evidence": "No cross-references found in other scripts",
      "impact30d": "Dead code; cognitive load for new developers",
      "reportedBy": "ng"
    },
    {
      "id": "NG-UNUSED-night-shift-automator",
      "description": "scripts/night-shift-automator.js is not referenced by any other script",
      "severity": 2,
      "evidence": "No cross-references found in other scripts",
      "impact30d": "Dead code; cognitive load for new developers",
      "reportedBy": "ng"
    },
    {
      "id": "NG-UNUSED-night-shift-scheduler",
      "description": "scripts/night-shift-scheduler.js is not referenced by any other script",
      "severity": 2,
      "evidence": "No cross-references found in other scripts",
      "impact30d": "Dead code; cognitive load for new developers",
      "reportedBy": "ng"
    },
    {
      "id": "NG-UNUSED-noesis-hook",
      "description": "scripts/noesis-hook.js is not referenced by any other script",
      "severity": 2,
      "evidence": "No cross-references found in other scripts",
      "impact30d": "Dead code; cognitive load for new developers",
      "reportedBy": "ng"
    },
    {
      "id": "NG-UNUSED-operator-noesis-engine",
      "description": "scripts/operator-noesis/operator-noesis-engine.js is not referenced by any other script",
      "severity": 2,
      "evidence": "No cross-references found in other scripts",
      "impact30d": "Dead code; cognitive load for new developers",
      "reportedBy": "ng"
    },
    {
      "id": "NG-UNUSED-package-synapse",
      "description": "scripts/package-synapse.js is not referenced by any other script",
      "severity": 2,
      "evidence": "No cross-references found in other scripts",
      "impact30d": "Dead code; cognitive load for new developers",
      "reportedBy": "ng"
    },
    {
      "id": "NG-UNUSED-profile-enricher",
      "description": "scripts/profile-enricher.js is not referenced by any other script",
      "severity": 2,
      "evidence": "No cross-references found in other scripts",
      "impact30d": "Dead code; cognitive load for new developers",
      "reportedBy": "ng"
    },
    {
      "id": "NG-UNUSED-rag-engine",
      "description": "scripts/rag-engine.js is not referenced by any other script",
      "severity": 2,
      "evidence": "No cross-references found in other scripts",
      "impact30d": "Dead code; cognitive load for new developers",
      "reportedBy": "ng"
    },
    {
      "id": "NG-UNUSED-semantic-lint",
      "description": "scripts/semantic-lint.js is not referenced by any other script",
      "severity": 2,
      "evidence": "No cross-references found in other scripts",
      "impact30d": "Dead code; cognitive load for new developers",
      "reportedBy": "ng"
    },
    {
      "id": "NG-UNUSED-skill-mapper",
      "description": "scripts/skill-mapper.js is not referenced by any other script",
      "severity": 2,
      "evidence": "No cross-references found in other scripts",
      "impact30d": "Dead code; cognitive load for new developers",
      "reportedBy": "ng"
    },
    {
      "id": "NG-UNUSED-squad-router",
      "description": "scripts/squad-router.js is not referenced by any other script",
      "severity": 2,
      "evidence": "No cross-references found in other scripts",
      "impact30d": "Dead code; cognitive load for new developers",
      "reportedBy": "ng"
    },
    {
      "id": "NG-UNUSED-upgrade-admin-produto-facilities",
      "description": "scripts/upgrade-admin-produto-facilities.js is not referenced by any other script",
      "severity": 2,
      "evidence": "No cross-references found in other scripts",
      "impact30d": "Dead code; cognitive load for new developers",
      "reportedBy": "ng"
    },
    {
      "id": "NG-UNUSED-upgrade-cs",
      "description": "scripts/upgrade-cs.js is not referenced by any other script",
      "severity": 2,
      "evidence": "No cross-references found in other scripts",
      "impact30d": "Dead code; cognitive load for new developers",
      "reportedBy": "ng"
    },
    {
      "id": "NG-UNUSED-upgrade-ops",
      "description": "scripts/upgrade-ops.js is not referenced by any other script",
      "severity": 2,
      "evidence": "No cross-references found in other scripts",
      "impact30d": "Dead code; cognitive load for new developers",
      "reportedBy": "ng"
    },
    {
      "id": "NG-UNUSED-validate-aiox-core-deps",
      "description": "scripts/validate-aiox-core-deps.js is not referenced by any other script",
      "severity": 2,
      "evidence": "No cross-references found in other scripts",
      "impact30d": "Dead code; cognitive load for new developers",
      "reportedBy": "ng"
    },
    {
      "id": "NG-UNUSED-validate-package-completeness",
      "description": "scripts/validate-package-completeness.js is not referenced by any other script",
      "severity": 2,
      "evidence": "No cross-references found in other scripts",
      "impact30d": "Dead code; cognitive load for new developers",
      "reportedBy": "ng"
    },
    {
      "id": "NG-UNUSED-vod-transcriber",
      "description": "scripts/vod-transcriber.js is not referenced by any other script",
      "severity": 2,
      "evidence": "No cross-references found in other scripts",
      "impact30d": "Dead code; cognitive load for new developers",
      "reportedBy": "ng"
    },
    {
      "id": "NG-UNUSED-clone-generator",
      "description": "scripts/evolution/clone-generator.js is not referenced by any other script",
      "severity": 2,
      "evidence": "No cross-references found in other scripts",
      "impact30d": "Dead code; cognitive load for new developers",
      "reportedBy": "ng"
    },
    {
      "id": "NG-UNUSED-cognitive-state-engine",
      "description": "scripts/evolution/cognitive-state-engine.js is not referenced by any other script",
      "severity": 2,
      "evidence": "No cross-references found in other scripts",
      "impact30d": "Dead code; cognitive load for new developers",
      "reportedBy": "ng"
    },
    {
      "id": "NG-UNUSED-generate-context",
      "description": "scripts/evolution/generate-context.js is not referenced by any other script",
      "severity": 2,
      "evidence": "No cross-references found in other scripts",
      "impact30d": "Dead code; cognitive load for new developers",
      "reportedBy": "ng"
    },
    {
      "id": "NG-UNUSED-metacognition-layer",
      "description": "scripts/evolution/metacognition-layer.js is not referenced by any other script",
      "severity": 2,
      "evidence": "No cross-references found in other scripts",
      "impact30d": "Dead code; cognitive load for new developers",
      "reportedBy": "ng"
    },
    {
      "id": "NG-UNUSED-noesis-pipeline",
      "description": "scripts/evolution/noesis-pipeline.js is not referenced by any other script",
      "severity": 2,
      "evidence": "No cross-references found in other scripts",
      "impact30d": "Dead code; cognitive load for new developers",
      "reportedBy": "ng"
    },
    {
      "id": "NG-UNUSED-noesis-status",
      "description": "scripts/evolution/noesis-status.js is not referenced by any other script",
      "severity": 2,
      "evidence": "No cross-references found in other scripts",
      "impact30d": "Dead code; cognitive load for new developers",
      "reportedBy": "ng"
    },
    {
      "id": "NG-UNUSED-notification-bridge",
      "description": "scripts/evolution/notification-bridge.js is not referenced by any other script",
      "severity": 2,
      "evidence": "No cross-references found in other scripts",
      "impact30d": "Dead code; cognitive load for new developers",
      "reportedBy": "ng"
    },
    {
      "id": "NG-UNUSED-validation-engine",
      "description": "scripts/evolution/validation-engine.js is not referenced by any other script",
      "severity": 2,
      "evidence": "No cross-references found in other scripts",
      "impact30d": "Dead code; cognitive load for new developers",
      "reportedBy": "ng"
    },
    {
      "id": "NG-UNUSED-verification-engine",
      "description": "scripts/evolution/verification-engine.js is not referenced by any other script",
      "severity": 2,
      "evidence": "No cross-references found in other scripts",
      "impact30d": "Dead code; cognitive load for new developers",
      "reportedBy": "ng"
    },
    {
      "id": "NG-UNUSED-operator-noesis-engine",
      "description": "scripts/operator-noesis/operator-noesis-engine.js is not referenced by any other script",
      "severity": 2,
      "evidence": "No cross-references found in other scripts",
      "impact30d": "Dead code; cognitive load for new developers",
      "reportedBy": "ng"
    }
  ],
  "topGaps": [
    {
      "id": "ILS-CONST-INCOMPLETE",
      "description": "Constitutional Layer missing one or more of the 5 Core Rules",
      "severity": 9,
      "evidence": "Not all RULE 1-5 markers found in constitutional-layer-v3.md",
      "impact30d": "Degraded reasoning quality; outputs may lack depth or evidence",
      "reportedBy": "sutskever"
    },
    {
      "id": "ILS-PROTO-INCOMPLETE",
      "description": "Constitutional Layer missing Protocol Extensions",
      "severity": 7,
      "evidence": "Not all P1-P5 protocol markers found",
      "impact30d": "Missing Karpathy anchoring, Ng workflows, or Nakajima self-improvement signals",
      "reportedBy": "sutskever"
    },
    {
      "id": "HAS-BASELINE-ZERO",
      "description": "Quality baseline not yet established — no session scores recorded",
      "severity": 7,
      "evidence": "current_baseline: 4.9, trend: establishing",
      "impact30d": "No quality trend tracking; unable to detect regression or improvement",
      "reportedBy": "hassabis"
    }
  ],
  "convergences": [],
  "divergences": [],
  "overallScore": 4.9,
  "memberScores": [
    {
      "memberId": "karpathy",
      "score": 0,
      "gapCount": 57
    },
    {
      "memberId": "sutskever",
      "score": 5,
      "gapCount": 2
    },
    {
      "memberId": "ng",
      "score": 2.400000000000011,
      "gapCount": 52
    },
    {
      "memberId": "hinton",
      "score": 7,
      "gapCount": 1
    },
    {
      "memberId": "hassabis",
      "score": 6,
      "gapCount": 2
    },
    {
      "memberId": "pedro",
      "score": 7,
      "gapCount": 1
    },
    {
      "memberId": "alan",
      "score": 6.5,
      "gapCount": 1
    },
    {
      "memberId": "distillation",
      "score": 5.3,
      "gapCount": 3
    }
  ],
  "totalGaps": 119,
  "timestamp": "2026-03-13T15:45:15.523Z"
}